<properties>
    <attributes name="appidkey" value="OnlineBanking"/>
    <attributes name="mwaddrkey" value="10.10.34.131"/>
    <attributes name="iospopuptransitioncorrection" value="true"/>
    <attributes name="isNewAppWithRespectToAndroidPackageName" value="true"/>
    <attributes name="iphonebundleversionkey" value="1.0"/>
    <attributes name="iosrespectimagesizecorrection" value="true"/>
    <attributes name="ioscheckboxcorrection" value="true"/>
    <attributes name="apppackagekey" value="com.orgname.OnlineBanking"/>
    <attributes name="winmangotiletitlekey" value="OnlineBanking"/>
    <attributes name="andtargetsdkkey" value="4.0 (14)"/>
    <attributes name="win8displaynamekey" value="OnlineBanking"/>
    <attributes name="android_allowselfsignedcertificates" value="None"/>
    <attributes name="iphonebundleidentifierkey" value="com.kony.OnlineBanking"/>
    <attributes name="appnamekey" value="OnlineBanking"/>
    <attributes name="currentgaversion" value="8.0.1.v201710100839"/>
    <attributes name="appversionkey" value="1.0.0"/>
    <attributes name="project.type" value="js"/>
    <attributes name="sessionmanager" value="Http Session Manager"/>
    <attributes name="vendornamekey" value="KonyLabs"/>
    <attributes name="appversioncode" value="1"/>
    <attributes name="createdgaversion" value="8.0.1"/>
    <attributes name="isDpScaleFactor" value="true"/>
    <attributes name="iostextboxpaddingcorrection" value="true"/>
    <attributes name="win6xj2meonlysupported" value="false"/>
    <attributes name="wp10displayname" value="OnlineBanking"/>
    <attributes name="referenceWidth" value="375"/>
    <attributes name="build" value="debug"/>
    <attributes name="studiovizproject" value="true"/>
    <attributes name="marginsincludedinwidgetcontainerweight" value="true"/>
    <attributes name="mwportkey" value="80"/>
    <attributes name="mwhttpsportkey" value="443"/>
</properties>